auto_tune/__init__.py
auto_tune/__main__.py
auto_tune/cli.py
auto_tune/search.py
auto_tune/evo/genes.py
auto_tune/evo/individual.py
auto_tune-0.0.2.dist-info/DESCRIPTION.rst
auto_tune-0.0.2.dist-info/METADATA
auto_tune-0.0.2.dist-info/RECORD
auto_tune-0.0.2.dist-info/WHEEL
auto_tune-0.0.2.dist-info/entry_points.txt
auto_tune-0.0.2.dist-info/metadata.json
auto_tune-0.0.2.dist-info/top_level.txt
