Metadata-Version: 2.0
Name: auto-tune
Version: 0.0.2
Summary: Estimate hyper-parameter search using evolutionary algorithms
Home-page: https://github.com/whitesmith/auto-tune
Author: Whitesmith, Lda
Author-email: services@whitesmith.co
License: MIT license
Platform: UNKNOWN
Classifier: Development Status :: 5 - Production/Stable
Classifier: Intended Audience :: Developers
Classifier: License :: OSI Approved :: MIT License
Classifier: Operating System :: Unix
Classifier: Operating System :: POSIX
Classifier: Operating System :: Microsoft :: Windows
Classifier: Programming Language :: Python
Classifier: Programming Language :: Python :: 2.7
Classifier: Programming Language :: Python :: 3
Classifier: Programming Language :: Python :: 3.4
Classifier: Programming Language :: Python :: 3.5
Classifier: Programming Language :: Python :: 3.6
Classifier: Programming Language :: Python :: Implementation :: CPython
Classifier: Topic :: Utilities
Requires-Dist: click
Requires-Dist: numpy
Requires-Dist: scikit-learn
Requires-Dist: scipy
